betterconfigs/__init__.py
betterconfigs/utilities.py
betterconfigs-0.8.4.dist-info/METADATA
betterconfigs-0.8.4.dist-info/WHEEL
betterconfigs-0.8.4.dist-info/licenses/LICENSE
betterconfigs-0.8.4.dist-info/RECORD
