Metadata-Version: 2.3
Name: betterconfigs
Version: 0.8.4
Summary: A small package to simplify configuration storing and retrieving
Project-URL: Homepage, https://github.com/iainrosen/betterconfigs
Project-URL: Bug Tracker, https://github.com/iainrosen/betterconfigs/issues
Author-email: Iain Rosen <hello@iainrosen.me>
License-File: LICENSE
Classifier: License :: OSI Approved :: GNU General Public License v3 (GPLv3)
Classifier: Operating System :: OS Independent
Classifier: Programming Language :: Python :: 3
Requires-Python: >=3.9
Requires-Dist: cryptography
